tivra/__init__.py
tivra/base.py
tivra/core.py
tivra/device.py
tivra/extractor.py
tivra/utils/__init__.py
tivra/utils/backends.py
tivra/utils/pyomo_generator.py
tivra-0.2.0.dist-info/METADATA
tivra-0.2.0.dist-info/WHEEL
tivra-0.2.0.dist-info/top_level.txt
tivra-0.2.0.dist-info/RECORD
