Metadata-Version: 2.2
Name: tivra
Version: 0.2.0
Summary: Tivra, a fast and agile solver based on PDHG, capable of running on multiple hardware accelerators
Requires-Python: <=3.12,>=3.10
Requires-Dist: highspy>=1.9.0
Requires-Dist: pyomo>=6.8.2
Requires-Dist: torch>=2.5.1
